s3sync.py
pys3sync-0.1.2.dist-info/LICENSE
pys3sync-0.1.2.dist-info/METADATA
pys3sync-0.1.2.dist-info/WHEEL
pys3sync-0.1.2.dist-info/entry_points.txt
pys3sync-0.1.2.dist-info/top_level.txt
pys3sync-0.1.2.dist-info/RECORD
