Metadata-Version: 2.1
Name: pys3sync
Version: 0.1.2
Summary: Continuously Sync local files to/from S3
Home-page: https://github.com/angadsingh/s3sync
Author: Angad Singh
Author-email: angad@angadsingh.in
License: MIT
Platform: UNKNOWN
Classifier: Programming Language :: Python :: 2
Classifier: Programming Language :: Python :: 3
Classifier: License :: OSI Approved :: MIT License
Classifier: Operating System :: OS Independent
Requires-Python: >=2.7
Requires-Dist: click
Requires-Dist: click-log
Requires-Dist: watchdog
Requires-Dist: pyyaml
Requires-Dist: token-bucket
Requires-Dist: pyformance
